LICENSE
MANIFEST.in
README.txt
VERSION
contributors.txt
setup.cfg
setup.py
geckoboard/__init__.py
geckoboard/geckoboard.py
geckoboard.egg-info/PKG-INFO
geckoboard.egg-info/SOURCES.txt
geckoboard.egg-info/dependency_links.txt
geckoboard.egg-info/requires.txt
geckoboard.egg-info/top_level.txt