Metadata-Version: 1.0
Name: geckoboard
Version: 0.8.6
Summary: Geckoboard API Interface (Unofficial)
Home-page: http://pypi.python.org/pypi/geckoboard/
Author: See Contributors
Author-email: napalm255@gmail.com
License: Apache License 2.0
Platform: UNKNOWN
